YTube/__init__.py
YTube-0.0.2.dist-info/LICENSE.txt
YTube-0.0.2.dist-info/METADATA
YTube-0.0.2.dist-info/WHEEL
YTube-0.0.2.dist-info/top_level.txt
YTube-0.0.2.dist-info/RECORD
