Metadata-Version: 2.1
Name: YTube
Version: 0.0.2
Summary: A simple Youtube Video Downloader.
Home-page: UNKNOWN
Author: Bestin Lalu
Author-email: bestinlalu.mec@gmail.com
License: MIT
Keywords: youtube
Platform: UNKNOWN
Classifier: Development Status :: 5 - Production/Stable
Classifier: Intended Audience :: Education
Classifier: Operating System :: Microsoft :: Windows :: Windows 10
Classifier: License :: OSI Approved :: MIT License
Classifier: Programming Language :: Python :: 3
Requires-Dist: pytube
